smev_agent_client/__init__.py
smev_agent_client/adapters.py
smev_agent_client/configuration.py
smev_agent_client/const.py
smev_agent_client/models.py
smev_agent_client/utils.py
smev_agent_client/contrib/__init__.py
smev_agent_client/contrib/my_edu/__init__.py
smev_agent_client/contrib/my_edu/interfaces/__init__.py
smev_agent_client/contrib/my_edu/interfaces/myedu.json
smev_agent_client/contrib/my_edu/interfaces/rest.py
smev_agent_client/contrib/my_edu/interfaces/utils.py
smev_agent_client/contrib/my_edu/interfaces/validation.py
smev_agent_client/interfaces/__init__.py
smev_agent_client/interfaces/base.py
smev_agent_client/interfaces/rest.py
smev_agent_client/logging/__init__.py
smev_agent_client/logging/base.py
smev_agent_client/logging/db.py
smev_agent_client/logging/stdlib.py
smev_agent_client/migrations/0001_initial.py
smev_agent_client/migrations/0002_auto_20220714_0650.py
smev_agent_client/migrations/__init__.py
smev_agent_client-0.4.0.dist-info/METADATA
smev_agent_client-0.4.0.dist-info/WHEEL
smev_agent_client-0.4.0.dist-info/dependency_links.txt
smev_agent_client-0.4.0.dist-info/top_level.txt
smev_agent_client-0.4.0.dist-info/RECORD
